befh/__init__.py
befh/cli.py
befh/core/__init__.py
befh/core/configuration.py
befh/core/runner.py
befh/exchange/__init__.py
befh/exchange/exchange.py
befh/exchange/rest_api_exchange.py
befh/exchange/websocket_exchange.py
befh/handler/__init__.py
befh/handler/handler.py
befh/handler/handler_operator.py
befh/handler/rotate_handler.py
befh/handler/sql_handler.py
befh/handler/zmq_handler.py
befh/table/__init__.py
befh/table/order_book_table.py
befh/table/table.py
BitcoinExchangeFH-2022.2.dist-info/LICENSE
BitcoinExchangeFH-2022.2.dist-info/METADATA
BitcoinExchangeFH-2022.2.dist-info/WHEEL
BitcoinExchangeFH-2022.2.dist-info/entry_points.txt
BitcoinExchangeFH-2022.2.dist-info/top_level.txt
BitcoinExchangeFH-2022.2.dist-info/RECORD
